fulladder.v
module half_adder(
    input a,b,
    output sum,carry
);
assign sum = a^b;
assign carry = a&b;

endmodule

module full_adder(
    input a,b,cin,
    output total_sum,cout
);
assign total_sum = a^b^cin;
assign cout = (a&b)|(cin & (a ^ b));
endmodule

fulladder_tb.v
`timescale 1ns/1ps

module fulladder_tb;
reg a,b,cin;
wire total_sum,cout;

full_adder uut(
    .a(a),
    .b(b),
    .cin(cin),
    .total_sum(total_sum),
    .cout(cout)
);
integer i;

  initial begin
    $dumpfile("full_adder.vcd");   // for waveform
    $dumpvars(0, fulladder_tb);

    $display("time | a b cin | sum cout");
    $display("-------------------------");

    
    for (i = 0; i < 8; i = i + 1) begin
      {a, b, cin} = i[2:0];
      #10;
      $display("%4t | %b %b  %b  |  %b    %b",
               $time, a, b, cin, total_sum, cout);
    end

    $finish;
  end
endmodule

full_adder.vcd
$date
	Tue Sep 30 10:08:10 2025
$end
$version
	Icarus Verilog
$end
$timescale
	1ps
$end
$scope module fulladder_tb $end
$var wire 1 ! cout $end
$var wire 1 " total_sum $end
$var reg 1 # a $end
$var reg 1 $ b $end
$var reg 1 % cin $end
$var integer 32 & i [31:0] $end
$scope module uut $end
$var wire 1 ' a $end
$var wire 1 ( b $end
$var wire 1 ) cin $end
$var wire 1 ! cout $end
$var wire 1 " total_sum $end
$upscope $end
$upscope $end
$enddefinitions $end
#0
$dumpvars
0)
0(
0'
b0 &
0%
0$
0#
0"
0!
$end
#10000
1"
1%
1)
b1 &
#20000
1"
1$
1(
0%
0)
b10 &
#30000
1!
0"
1%
1)
b11 &
#40000
0!
1"
1#
1'
0$
0(
0%
0)
b100 &
#50000
1!
0"
1%
1)
b101 &
#60000
0"
1$
1(
0%
0)
b110 &
#70000
1"
1%
1)
b111 &
#80000
b1000 &
