fullsub.v
module full_subtractor(
    input a, b, bin,
    output diff, bout
);
assign diff = a ^ b ^ bin;  
assign bout = (~a & b) | (bin & ~(a ^ b));  

endmodule

fullsub_tb.v
`timescale 1ns/1ps

module fullsub_tb;
reg a, b, bin;
wire diff, bout;

full_subtractor uut (
    .a(a),
    .b(b),
    .bin(bin),
    .diff(diff),
    .bout(bout)
);

integer i;

initial begin
    $dumpfile("full_subtractor.vcd");   // for waveform
    $dumpvars(0, fullsub_tb);

    $display("time | a b bin | diff bout");
    $display("--------------------------");

    for (i = 0; i < 8; i = i + 1) begin
      {a, b, bin} = i[2:0];
      #10;
      $display("%4t | %b %b  %b  |   %b    %b",
               $time, a, b, bin, diff, bout);
    end

    $finish;
end
endmodule

full_subtractor.vcd
$date
	Fri Oct 03 07:51:56 2025
$end
$version
	Icarus Verilog
$end
$timescale
	1ps
$end
$scope module fullsub_tb $end
$var wire 1 ! bout $end
$var wire 1 " diff $end
$var reg 1 # a $end
$var reg 1 $ b $end
$var reg 1 % bin $end
$var integer 32 & i [31:0] $end
$scope module uut $end
$var wire 1 ' a $end
$var wire 1 ( b $end
$var wire 1 ) bin $end
$var wire 1 ! bout $end
$var wire 1 " diff $end
$upscope $end
$upscope $end
$enddefinitions $end
#0
$dumpvars
0)
0(
0'
b0 &
0%
0$
0#
0"
0!
$end
#10000
1!
1"
1%
1)
b1 &
#20000
1"
1$
1(
0%
0)
b10 &
#30000
0"
1%
1)
b11 &
#40000
0!
1"
1#
1'
0$
0(
0%
0)
b100 &
#50000
0"
1%
1)
b101 &
#60000
0"
1$
1(
0%
0)
b110 &
#70000
1!
1"
1%
1)
b111 &
#80000
b1000 &
