four_one.v
module two_one_mux(
    input  i0, i1, s0,
    output y
);
  assign y = (~s0 & i0) | (s0 & i1);
endmodule

module four_one_mux_2x1 (
    input  i0, i1, i2, i3,   // data inputs
    input  s1, s0,           // select lines
    output y                 // output
);
  wire y0, y1;
  two_one_mux m1 (.i0(i0), .i1(i1), .s0(s0), .y(y0));
  two_one_mux m2 (.i0(i2), .i1(i3), .s0(s0), .y(y1));
 two_one_mux m3 (.i0(y0), .i1(y1), .s0(s1), .y(y));
endmodule

mux_tb.v
`timescale 1ns/1ps

module two_one_mux_tb;
  reg  i0, i1, s0;
  wire y;

  // DUT
  two_one_mux uut(.i0(i0), .i1(i1), .s0(s0), .y(y));

  integer i;
  reg exp;

  initial begin
    $dumpfile("mux.vcd");
    $dumpvars(0, two_one_mux_tb);

    $display(" time | i0 i1 s0 | y  exp | pass?");
    $display("-----------------------------------");

    for (i = 0; i < 8; i = i + 1) begin
      {i0, i1, s0} = i[2:0];   // iterate all combinations
      #1;                      // allow signals to settle
      exp = s0 ? i1 : i0;      // golden model

      $display("%4t |  %b  %b  %b | %b   %b  | %s",
               $time, i0, i1, s0, y, exp, (y===exp) ? "PASS" : "FAIL");

      #9;                      // step to next 10ns boundary
    end

    $finish;
  end
endmodule

mux.vcd
$date
	Fri Oct 03 08:49:51 2025
$end
$version
	Icarus Verilog
$end
$timescale
	1ps
$end
$scope module two_one_mux_tb $end
$var wire 1 ! y $end
$var reg 1 " exp $end
$var integer 32 # i [31:0] $end
$var reg 1 $ i0 $end
$var reg 1 % i1 $end
$var reg 1 & s0 $end
$scope module uut $end
$var wire 1 ' i0 $end
$var wire 1 ( i1 $end
$var wire 1 ) s0 $end
$var wire 1 ! y $end
$upscope $end
$upscope $end
$enddefinitions $end
#0
$dumpvars
0)
0(
0'
0&
0%
0$
b0 #
x"
0!
$end
#1000
0"
#10000
1&
1)
b1 #
#20000
1%
1(
0&
0)
b10 #
#30000
1!
1&
1)
b11 #
#31000
1"
#40000
1$
1'
0%
0(
0&
0)
b100 #
#50000
0!
1&
1)
b101 #
#51000
0"
#60000
1!
1%
1(
0&
0)
b110 #
#61000
1"
#70000
1&
1)
b111 #
#80000
b1000 #
